README.md
setup.py
spotixplore/__init__.py
spotixplore/credentials.py
spotixplore/main.py
spotixplore/starting_point.py
spotixplore.egg-info/PKG-INFO
spotixplore.egg-info/SOURCES.txt
spotixplore.egg-info/dependency_links.txt
spotixplore.egg-info/requires.txt
spotixplore.egg-info/top_level.txt
spotixplore/classes/__init__.py
spotixplore/classes/artist_class.py
spotixplore/classes/track_class.py
spotixplore/extraction/__init__.py
spotixplore/extraction/get_artists.py
spotixplore/extraction/get_recommended_tracks.py
spotixplore/extraction/get_tracks.py
spotixplore/output/__init__.py
spotixplore/output/dataframing.py
spotixplore/output/graph.py